aagdpr/__init__.py
aagdpr/app_settings.py
aagdpr/apps.py
aagdpr/locale/en/LC_MESSAGES/django.mo
aagdpr/locale/en/LC_MESSAGES/django.po
aagdpr/static/aagdpr/ajax/libs/Chart.js/4.4.1/chart.umd.js
aagdpr/static/aagdpr/ajax/libs/Chart.js/4.4.1/chart.umd.js.map
aagdpr/static/aagdpr/ajax/libs/bootstrap/5.3.3/css/bootstrap.min.css
aagdpr/static/aagdpr/ajax/libs/bootstrap/5.3.3/css/bootstrap.min.css.map
aagdpr/static/aagdpr/ajax/libs/bootstrap/5.3.3/js/bootstrap.bundle.min.js
aagdpr/static/aagdpr/ajax/libs/bootstrap/5.3.3/js/bootstrap.bundle.min.js.map
aagdpr/static/aagdpr/ajax/libs/bootstrap/5.3.3/js/bootstrap.min.js
aagdpr/static/aagdpr/ajax/libs/bootstrap/5.3.3/js/bootstrap.min.js.map
aagdpr/static/aagdpr/ajax/libs/bootstrap/5.3.7/css/bootstrap.min.css
aagdpr/static/aagdpr/ajax/libs/bootstrap/5.3.7/css/bootstrap.min.css.map
aagdpr/static/aagdpr/ajax/libs/bootstrap/5.3.7/js/bootstrap.bundle.js
aagdpr/static/aagdpr/ajax/libs/bootstrap/5.3.7/js/bootstrap.bundle.js.map
aagdpr/static/aagdpr/ajax/libs/bootstrap/5.3.7/js/bootstrap.min.js
aagdpr/static/aagdpr/ajax/libs/bootstrap/5.3.7/js/bootstrap.min.js.map
aagdpr/static/aagdpr/ajax/libs/bootswatch/5.3.3/darkly/_bootswatch.scss
aagdpr/static/aagdpr/ajax/libs/bootswatch/5.3.3/darkly/_variables.scss
aagdpr/static/aagdpr/ajax/libs/bootswatch/5.3.3/darkly/bootstrap.css
aagdpr/static/aagdpr/ajax/libs/bootswatch/5.3.3/darkly/bootstrap.min.css
aagdpr/static/aagdpr/ajax/libs/bootswatch/5.3.3/darkly/bootstrap.min.css.map
aagdpr/static/aagdpr/ajax/libs/bootswatch/5.3.3/darkly/bootstrap.rtl.css
aagdpr/static/aagdpr/ajax/libs/bootswatch/5.3.3/darkly/bootstrap.rtl.min.css
aagdpr/static/aagdpr/ajax/libs/bootswatch/5.3.3/darkly/fonts-lato.css
aagdpr/static/aagdpr/ajax/libs/bootswatch/5.3.3/darkly/fonts-lato.min.css
aagdpr/static/aagdpr/ajax/libs/bootswatch/5.3.3/flatly/_bootswatch.scss
aagdpr/static/aagdpr/ajax/libs/bootswatch/5.3.3/flatly/_variables.scss
aagdpr/static/aagdpr/ajax/libs/bootswatch/5.3.3/flatly/bootstrap.css
aa_gdpr-0.7.1.dist-info/licenses/LICENSE
aa_gdpr-0.7.1.dist-info/WHEEL
aa_gdpr-0.7.1.dist-info/METADATA
aa_gdpr-0.7.1.dist-info/RECORD
